[
  {
    "id": "EMAIL-001",
    "from": "tanaka.yuki@hankyuhanshin-exp.co.jp",
    "from_name": "田中 裕樹",
    "to": ["suzuki.kenji@hankyuhanshin-exp.co.jp"],
    "cc": [],
    "date": "2026-01-08T09:15:00+09:00",
    "subject": "【入札依頼】トヨタ自動車様 2026年度上期 海上輸送入札",
    "body": "鈴木課長\n\nお疲れ様です。田中です。\n\nトヨタ自動車様より、2026年度上期（4月～9月）の海上輸送に関する入札依頼が届きました。\n対象航路は以下の通りです：\n\n1. 名古屋 → 上海（FCL 40'）\n2. 名古屋 → 天津（FCL 40'）\n3. 横浜 → バンコク（FCL 20'/40'）\n4. 神戸 → ホーチミン（LCL）\n\n提出期限：2026年1月31日\nフォーマット：顧客指定Excel（添付ファイル参照）\n\n各航路の最新費率を購買部門へ確認をお願いいたします。\n\nよろしくお願いいたします。",
    "has_attachment": true,
    "attachment_names": ["トヨタ_2026上期_入札フォーマット.xlsx"],
    "language": "ja",
    "category": "bidding_request",
    "tags": ["入札", "トヨタ", "海上輸送", "FCL", "LCL"]
  },
  {
    "id": "EMAIL-002",
    "from": "suzuki.kenji@hankyuhanshin-exp.co.jp",
    "from_name": "鈴木 健二",
    "to": ["wang.lei@hankyuhanshin-sh.cn"],
    "cc": ["tanaka.yuki@hankyuhanshin-exp.co.jp"],
    "date": "2026-01-08T10:30:00+09:00",
    "subject": "【見積依頼】名古屋→上海/天津 FCL 40' 最新費率確認",
    "body": "王磊さん\n\nお疲れ様です。鈴木です。\n\nトヨタ自動車様の入札対応のため、以下の航路の最新費率をご確認ください。\n\n①名古屋→上海 FCL 40'\n②名古屋→天津 FCL 40'\n\n必要情報：\n・海上運賃（Ocean Freight）\n・BAF/CAF\n・THC（積地/揚地）\n・DOC Fee\n・有効期間\n\n1月15日までにご回答いただけると助かります。\nよろしくお願いいたします。",
    "has_attachment": false,
    "attachment_names": [],
    "language": "ja",
    "category": "rate_inquiry",
    "tags": ["見積", "名古屋", "上海", "天津", "FCL"]
  },
  {
    "id": "EMAIL-003",
    "from": "wang.lei@hankyuhanshin-sh.cn",
    "from_name": "王磊",
    "to": ["suzuki.kenji@hankyuhanshin-exp.co.jp"],
    "cc": ["tanaka.yuki@hankyuhanshin-exp.co.jp"],
    "date": "2026-01-12T14:20:00+08:00",
    "subject": "Re: 【見積依頼】名古屋→上海/天津 FCL 40' 最新費率確認",
    "body": "鈴木課長\n\n上海事務所の王です。費率確認できましたのでご連絡いたします。\n\n①名古屋→上海 FCL 40'\n  Ocean Freight: USD 850/40'\n  BAF: USD 120/40'\n  THC(名古屋): JPY 35,000/40'\n  THC(上海): CNY 800/40'\n  DOC Fee: USD 35/BL\n  有効期間: 2026/04/01 - 2026/06/30\n\n②名古屋→天津 FCL 40'\n  Ocean Freight: USD 920/40'\n  BAF: USD 135/40'\n  THC(名古屋): JPY 35,000/40'\n  THC(天津): CNY 850/40'\n  DOC Fee: USD 35/BL\n  有効期間: 2026/04/01 - 2026/06/30\n\n船社はONE(Ocean Network Express)とCOSCOの2社から取得しています。\n上記はONEの費率です。COSCOは若干安いですが、スペース確保が不安定です。\n\nご不明点がございましたら、お気軽にお問い合わせください。",
    "has_attachment": false,
    "attachment_names": [],
    "language": "ja",
    "category": "rate_response",
    "tags": ["費率回答", "名古屋", "上海", "天津", "ONE", "COSCO"]
  },
  {
    "id": "EMAIL-004",
    "from": "suzuki.kenji@hankyuhanshin-exp.co.jp",
    "from_name": "鈴木 健二",
    "to": ["nguyen.van.duc@hankyuhanshin-vn.com"],
    "cc": ["tanaka.yuki@hankyuhanshin-exp.co.jp"],
    "date": "2026-01-08T11:00:00+09:00",
    "subject": "Quote Request: Kobe → Ho Chi Minh LCL Rate",
    "body": "Dear Duc,\n\nCould you please provide the latest LCL rate for the following lane?\n\nOrigin: Kobe, Japan\nDestination: Ho Chi Minh City, Vietnam\nCargo Type: LCL (General Cargo)\n\nPlease include:\n- Ocean Freight (per CBM/RT)\n- Local charges at destination\n- CFS charges\n- Validity period\n\nWe need this for a customer bid due Jan 31.\nPlease reply by Jan 15 if possible.\n\nBest regards,\nKenji Suzuki",
    "has_attachment": false,
    "attachment_names": [],
    "language": "en",
    "category": "rate_inquiry",
    "tags": ["quote", "Kobe", "Ho Chi Minh", "LCL"]
  },
  {
    "id": "EMAIL-005",
    "from": "nguyen.van.duc@hankyuhanshin-vn.com",
    "from_name": "Nguyen Van Duc",
    "to": ["suzuki.kenji@hankyuhanshin-exp.co.jp"],
    "cc": [],
    "date": "2026-01-13T16:45:00+07:00",
    "subject": "Re: Quote Request: Kobe → Ho Chi Minh LCL Rate",
    "body": "Dear Suzuki-san,\n\nPlease find the LCL rates for Kobe → Ho Chi Minh below:\n\nOcean Freight: USD 45/CBM (min 1 CBM)\nCFS Charge (Origin): JPY 3,500/RT\nCFS Charge (Destination): USD 8/RT\nD/O Fee: USD 40/BL\nHandling Fee: USD 25/shipment\nCustoms Clearance: USD 60/shipment\n\nValidity: April 1 - June 30, 2026\nTransit Time: approx. 12-14 days\nCarrier: Evergreen / Wan Hai\n\nNote: Rates may vary for hazardous or oversized cargo.\n\nPlease let me know if you need any further information.\n\nBest regards,\nDuc Nguyen\nHankyu Hanshin Express (Vietnam)",
    "has_attachment": false,
    "attachment_names": [],
    "language": "en",
    "category": "rate_response",
    "tags": ["rate_reply", "Kobe", "Ho Chi Minh", "LCL", "Evergreen", "Wan Hai"]
  },
  {
    "id": "EMAIL-006",
    "from": "li.wei@hankyuhanshin-bj.cn",
    "from_name": "李伟",
    "to": ["suzuki.kenji@hankyuhanshin-exp.co.jp"],
    "cc": ["fukuyama.akira@hankyuhanshin-exp.co.jp"],
    "date": "2026-01-15T09:30:00+08:00",
    "subject": "横浜→バンコク FCL費率 回答",
    "body": "鈴木さん\n\nお疲れ様です。北京の李です。\nバンコク向けの費率について、タイ現法から回答がありましたので転送します。\n\n横浜→バンコク（レムチャバン港）\n\nFCL 20':\n  Ocean Freight: USD 380/20'\n  BAF: USD 65/20'\n  THC(横浜): JPY 25,000/20'\n  THC(レムチャバン): THB 4,500/20'\n\nFCL 40':\n  Ocean Freight: USD 580/40'\n  BAF: USD 95/40'\n  THC(横浜): JPY 35,000/40'\n  THC(レムチャバン): THB 6,800/40'\n\n共通:\n  DOC Fee: USD 35/BL\n  Seal Fee: JPY 1,500/container\n  有効期間: 2026/04/01 - 2026/09/30\n  船社: NYK / Hapag-Lloyd\n  トランジットタイム: 約14-16日\n\nよろしくお願いいたします。",
    "has_attachment": false,
    "attachment_names": [],
    "language": "ja",
    "category": "rate_response",
    "tags": ["費率回答", "横浜", "バンコク", "FCL", "NYK", "Hapag-Lloyd"]
  },
  {
    "id": "EMAIL-007",
    "from": "tanaka.yuki@hankyuhanshin-exp.co.jp",
    "from_name": "田中 裕樹",
    "to": ["suzuki.kenji@hankyuhanshin-exp.co.jp"],
    "cc": [],
    "date": "2026-01-20T08:45:00+09:00",
    "subject": "トヨタ様入札 費率入力完了報告",
    "body": "鈴木課長\n\nお疲れ様です。田中です。\n\n各拠点からの費率回答をもとに、トヨタ様指定フォーマットへの入力が完了しました。\n\n入力内容のサマリー：\n・名古屋→上海 FCL 40': USD 850 + surcharges\n・名古屋→天津 FCL 40': USD 920 + surcharges\n・横浜→バンコク FCL 20': USD 380 / 40': USD 580 + surcharges\n・神戸→ホーチミン LCL: USD 45/CBM\n\nご確認のうえ、問題なければ顧客へ提出いたします。\n添付にて入力済みExcelをお送りします。\n\n提出期限：1月31日\n\nよろしくお願いいたします。",
    "has_attachment": true,
    "attachment_names": ["トヨタ_2026上期_入札回答_v1.xlsx"],
    "language": "ja",
    "category": "internal_report",
    "tags": ["入札回答", "トヨタ", "確認依頼"]
  },
  {
    "id": "EMAIL-008",
    "from": "chen.ming@hankyuhanshin-sh.cn",
    "from_name": "陈明",
    "to": ["fukuyama.akira@hankyuhanshin-exp.co.jp", "suzuki.kenji@hankyuhanshin-exp.co.jp"],
    "cc": [],
    "date": "2026-01-22T10:00:00+08:00",
    "subject": "关于2月份上海出口运价上涨通知",
    "body": "福山部长、鈴木课长：\n\n你们好，上海办事处的陈明。\n\n接到主要船公司通知，2月起上海出口各航线运价将有所调整：\n\n1. 上海→大阪/神户\n   - FCL 20': 上涨 USD 50\n   - FCL 40': 上涨 USD 80\n   原因：春节后出货高峰，舱位紧张\n\n2. 上海→东京/横浜\n   - FCL 20': 上涨 USD 40\n   - FCL 40': 上涨 USD 65\n\n3. 上海→名古屋\n   - 暂时维持不变\n\n涉及船公司：COSCO、ONE、Evergreen\n新价格有效期：2026/02/01 - 2026/03/31\n\n建议在此期间如有客户询价，参考上调后的费率报价。\n如需详细费率表请告知，我整理后发过来。\n\n此致",
    "has_attachment": false,
    "attachment_names": [],
    "language": "zh",
    "category": "rate_change_notice",
    "tags": ["运价上涨", "上海", "大阪", "神户", "东京", "COSCO", "ONE"]
  },
  {
    "id": "EMAIL-009",
    "from": "honda.procurement@honda.co.jp",
    "from_name": "本田技研工業 調達部",
    "to": ["tanaka.yuki@hankyuhanshin-exp.co.jp"],
    "cc": [],
    "date": "2026-02-03T13:00:00+09:00",
    "subject": "【RFQ】Honda 2026年度 航空輸送見積依頼",
    "body": "阪急阪神エクスプレス\n田中様\n\n平素よりお世話になっております。\n本田技研工業 調達部でございます。\n\n2026年度の航空輸送につきまして、下記の通り見積をお願いいたします。\n\n対象ルート：\n1. 成田(NRT) → ロサンゼルス(LAX)  一般貨物 100kg+\n2. 成田(NRT) → シカゴ(ORD)  一般貨物 300kg+\n3. 関空(KIX) → バンコク(BKK)  自動車部品 500kg+\n4. 成田(NRT) → 上海浦東(PVG)  電子部品 45kg+\n\n必要項目：\n・航空運賃（Air Freight Rate）/kg\n・FSC（Fuel Surcharge）\n・AWC（Air Waybill Charge）\n・ターミナルハンドリング\n・通関費用\n・トランジットタイム\n\n回答期限：2026年2月20日\nフォーマット：添付Excel\n\n何卒よろしくお願いいたします。",
    "has_attachment": true,
    "attachment_names": ["Honda_AirFreight_RFQ_2026.xlsx"],
    "language": "ja",
    "category": "bidding_request",
    "tags": ["入札", "Honda", "航空輸送", "NRT", "LAX", "ORD", "BKK", "PVG"]
  },
  {
    "id": "EMAIL-010",
    "from": "tanaka.yuki@hankyuhanshin-exp.co.jp",
    "from_name": "田中 裕樹",
    "to": ["kim.soojin@hankyuhanshin-kr.com"],
    "cc": ["suzuki.kenji@hankyuhanshin-exp.co.jp"],
    "date": "2026-02-04T09:00:00+09:00",
    "subject": "【航空運賃確認】NRT→LAX / NRT→ORD 最新レート",
    "body": "金秀珍さん\n\nお疲れ様です。田中です。\n\n本田技研様よりRFQ（航空）が届きました。\n韓国経由便も含め、以下ルートの最新航空運賃を確認お願いします。\n\n①成田→ロサンゼルス 一般貨物 100kg+\n②成田→シカゴ 一般貨物 300kg+\n\n利用キャリア候補：ANA Cargo / JAL Cargo / Korean Air Cargo\n\n2月14日までにご回答お願いいたします。",
    "has_attachment": false,
    "attachment_names": [],
    "language": "ja",
    "category": "rate_inquiry",
    "tags": ["航空運賃", "NRT", "LAX", "ORD", "ANA", "JAL", "Korean Air"]
  },
  {
    "id": "EMAIL-011",
    "from": "kim.soojin@hankyuhanshin-kr.com",
    "from_name": "Kim Soojin",
    "to": ["tanaka.yuki@hankyuhanshin-exp.co.jp"],
    "cc": ["suzuki.kenji@hankyuhanshin-exp.co.jp"],
    "date": "2026-02-12T15:30:00+09:00",
    "subject": "Re: 【航空運賃確認】NRT→LAX / NRT→ORD 最新レート",
    "body": "田中さん\n\nソウルの金です。航空運賃の確認結果をお送りします。\n\n①成田→ロサンゼルス (100kg+)\n  ANA Cargo: JPY 780/kg + FSC JPY 180/kg\n  Korean Air (ICN経由): JPY 650/kg + FSC JPY 160/kg\n  ※Korean Air経由の場合、T/T +1日\n\n②成田→シカゴ (300kg+)\n  JAL Cargo: JPY 850/kg + FSC JPY 195/kg\n  Korean Air (ICN経由): JPY 720/kg + FSC JPY 175/kg\n\n共通チャージ：\n  AWC: JPY 3,000/件\n  Terminal Handling: JPY 15/kg (min JPY 3,000)\n  有効期間: 2026/04/01 - 2026/06/30\n\nKorean Air経由はコスト面で有利ですが、仁川でのトランジットが発生します。\nお客様の納期要件次第でご判断ください。\n\nよろしくお願いいたします。",
    "has_attachment": false,
    "attachment_names": [],
    "language": "ja",
    "category": "rate_response",
    "tags": ["航空運賃回答", "NRT", "LAX", "ORD", "ANA", "JAL", "Korean Air"]
  },
  {
    "id": "EMAIL-012",
    "from": "wang.lei@hankyuhanshin-sh.cn",
    "from_name": "王磊",
    "to": ["tanaka.yuki@hankyuhanshin-exp.co.jp"],
    "cc": [],
    "date": "2026-02-13T11:00:00+08:00",
    "subject": "NRT→PVG 航空运费报价",
    "body": "田中さん\n\n上海の王です。成田→上海浦東の航空運賃です。\n\nNRT → PVG（電子部品 45kg+）\n  ANA Cargo: JPY 420/kg + FSC JPY 95/kg\n  中国国際航空(Air China): JPY 350/kg + FSC JPY 85/kg\n  Spring Japan (LCC): JPY 280/kg + FSC JPY 70/kg\n  ※Spring Japanは重量制限あり、100kg以上は要問合せ\n\n  AWC: JPY 2,500/件\n  Terminal Handling: JPY 12/kg\n  通関費用（上海側）: CNY 500/shipment\n  有効期間: 2026/04/01 - 2026/06/30\n  T/T: 1-2日（直行便）\n\n電子部品の場合、リチウムバッテリー含有の有無をご確認ください。\n含有の場合、DG surchargeが別途発生します。\n\nよろしくお願いいたします。",
    "has_attachment": false,
    "attachment_names": [],
    "language": "ja",
    "category": "rate_response",
    "tags": ["航空運賃回答", "NRT", "PVG", "電子部品", "ANA", "Air China"]
  },
  {
    "id": "EMAIL-013",
    "from": "fukuyama.akira@hankyuhanshin-exp.co.jp",
    "from_name": "福山 明",
    "to": ["suzuki.kenji@hankyuhanshin-exp.co.jp", "tanaka.yuki@hankyuhanshin-exp.co.jp"],
    "cc": [],
    "date": "2026-02-15T08:30:00+09:00",
    "subject": "【重要】2026年度 GRI通知 アジア→欧州航路",
    "body": "各位\n\n福山です。\n\n主要船社よりGRI（General Rate Increase）の通知がありましたので共有します。\n\n対象航路：アジア→欧州（全般）\n実施日：2026年3月1日\n\n値上げ幅：\n・FCL 20': USD 200/TEU\n・FCL 40': USD 400/FEU\n\n対象船社：\n・Maersk\n・MSC\n・CMA CGM\n・Hapag-Lloyd\n\n現在有効な見積が影響を受ける可能性があります。\n該当顧客への事前連絡をお願いいたします。\n\n特にパナソニック様、日立様の欧州向け案件は要注意です。\n\n以上",
    "has_attachment": false,
    "attachment_names": [],
    "language": "ja",
    "category": "rate_change_notice",
    "tags": ["GRI", "アジア", "欧州", "Maersk", "MSC", "CMA CGM", "Hapag-Lloyd"]
  },
  {
    "id": "EMAIL-014",
    "from": "panasonic.logistics@panasonic.com",
    "from_name": "パナソニック ロジスティクス部",
    "to": ["suzuki.kenji@hankyuhanshin-exp.co.jp"],
    "cc": [],
    "date": "2026-02-18T10:00:00+09:00",
    "subject": "【入札】パナソニック 2026年度 欧州向け海上輸送 見積依頼",
    "body": "阪急阪神エクスプレス\n鈴木様\n\nいつもお世話になっております。\nパナソニック ロジスティクス部でございます。\n\n2026年度の欧州向け海上輸送につきまして、見積を依頼いたします。\n\n対象航路：\n1. 大阪→ハンブルク FCL 40'HC\n2. 大阪→ロッテルダム FCL 40'HC\n3. 東京→フェリクストウ FCL 40'\n4. 名古屋→ブレーメン FCL 20'\n\n貨物：家電製品（一般貨物）\n数量：月間約 10-15 TEU\n\n回答期限：2026年3月5日\nフォーマット：添付をご使用ください\n\n何卒よろしくお願いいたします。",
    "has_attachment": true,
    "attachment_names": ["Panasonic_EU_SeaFreight_2026.xlsx"],
    "language": "ja",
    "category": "bidding_request",
    "tags": ["入札", "パナソニック", "欧州", "ハンブルク", "ロッテルダム", "FCL"]
  },
  {
    "id": "EMAIL-015",
    "from": "suzuki.kenji@hankyuhanshin-exp.co.jp",
    "from_name": "鈴木 健二",
    "to": ["mueller.hans@hankyuhanshin-de.com"],
    "cc": ["fukuyama.akira@hankyuhanshin-exp.co.jp"],
    "date": "2026-02-19T09:00:00+09:00",
    "subject": "Rate Request: Osaka/Tokyo → Hamburg/Rotterdam/Felixstowe/Bremen",
    "body": "Dear Hans,\n\nWe have received an RFQ from Panasonic for their 2026 Europe-bound sea freight.\nCould you please check the latest rates for the following lanes?\n\n1. Osaka → Hamburg FCL 40'HC\n2. Osaka → Rotterdam FCL 40'HC\n3. Tokyo → Felixstowe FCL 40'\n4. Nagoya → Bremen FCL 20'\n\nCargo: Home electronics (general cargo)\nVolume: approx. 10-15 TEU/month\n\nPlease include all surcharges (BAF, CAF, THC, ISPS, etc.)\nWe need your reply by Feb 28 at the latest.\n\nIMPORTANT: Please note the recent GRI effective March 1st.\nMake sure the rates reflect post-GRI levels.\n\nThank you,\nKenji Suzuki",
    "has_attachment": false,
    "attachment_names": [],
    "language": "en",
    "category": "rate_inquiry",
    "tags": ["rate_request", "Europe", "Hamburg", "Rotterdam", "Felixstowe", "Bremen", "Panasonic"]
  },
  {
    "id": "EMAIL-016",
    "from": "mueller.hans@hankyuhanshin-de.com",
    "from_name": "Hans Mueller",
    "to": ["suzuki.kenji@hankyuhanshin-exp.co.jp"],
    "cc": ["fukuyama.akira@hankyuhanshin-exp.co.jp"],
    "date": "2026-02-26T17:00:00+01:00",
    "subject": "Re: Rate Request: Osaka/Tokyo → Hamburg/Rotterdam/Felixstowe/Bremen",
    "body": "Dear Suzuki-san,\n\nPlease find the updated rates below (post-GRI, effective March 1st):\n\n1. Osaka → Hamburg FCL 40'HC\n   Ocean Freight: USD 2,450/40'HC\n   BAF: USD 380/40'HC\n   CAF: 3%\n   THC (Osaka): JPY 42,000\n   THC (Hamburg): EUR 280\n   ISPS: EUR 15\n\n2. Osaka → Rotterdam FCL 40'HC\n   Ocean Freight: USD 2,350/40'HC\n   BAF: USD 365/40'HC\n   CAF: 3%\n   THC (Osaka): JPY 42,000\n   THC (Rotterdam): EUR 265\n   ISPS: EUR 15\n\n3. Tokyo → Felixstowe FCL 40'\n   Ocean Freight: USD 2,280/40'\n   BAF: USD 350/40'\n   THC (Tokyo): JPY 38,000\n   THC (Felixstowe): GBP 220\n\n4. Nagoya → Bremen FCL 20'\n   Ocean Freight: USD 1,350/20'\n   BAF: USD 195/20'\n   THC (Nagoya): JPY 25,000\n   THC (Bremen): EUR 185\n\nAll rates valid: 2026/04/01 - 2026/09/30\nCarriers: Maersk, Hapag-Lloyd\nTransit: 35-40 days via Suez\n\nBest regards,\nHans Mueller\nHankyu Hanshin Express (Germany)",
    "has_attachment": false,
    "attachment_names": [],
    "language": "en",
    "category": "rate_response",
    "tags": ["rate_reply", "Hamburg", "Rotterdam", "Felixstowe", "Bremen", "Maersk", "Hapag-Lloyd"]
  },
  {
    "id": "EMAIL-017",
    "from": "suzuki.kenji@hankyuhanshin-exp.co.jp",
    "from_name": "鈴木 健二",
    "to": ["panasonic.logistics@panasonic.com"],
    "cc": ["tanaka.yuki@hankyuhanshin-exp.co.jp", "fukuyama.akira@hankyuhanshin-exp.co.jp"],
    "date": "2026-03-03T10:00:00+09:00",
    "subject": "Re: 【入札】パナソニック 2026年度 欧州向け海上輸送 見積回答",
    "body": "パナソニック ロジスティクス部 御中\n\nいつもお世話になっております。\n阪急阪神エクスプレスの鈴木でございます。\n\n2026年度欧州向け海上輸送の見積を添付にてご提出いたします。\n\n主要費率サマリー：\n1. 大阪→ハンブルク 40'HC: USD 2,450 + surcharges\n2. 大阪→ロッテルダム 40'HC: USD 2,350 + surcharges\n3. 東京→フェリクストウ 40': USD 2,280 + surcharges\n4. 名古屋→ブレーメン 20': USD 1,350 + surcharges\n\n有効期間: 2026/04/01 - 2026/09/30\n※3月1日付GRI反映済み\n\nご不明点がございましたら、何なりとお申し付けください。\n\n何卒よろしくお願いいたします。",
    "has_attachment": true,
    "attachment_names": ["Panasonic_EU_SeaFreight_2026_HHE回答.xlsx"],
    "language": "ja",
    "category": "bidding_response",
    "tags": ["入札回答", "パナソニック", "欧州"]
  },
  {
    "id": "EMAIL-018",
    "from": "zhang.wei@customer-abc.cn",
    "from_name": "张伟",
    "to": ["wang.lei@hankyuhanshin-sh.cn"],
    "cc": [],
    "date": "2026-02-20T14:00:00+08:00",
    "subject": "ABC电子 2026年Q2海运询价",
    "body": "王磊先生：\n\n您好！\n\n我司ABC电子计划在2026年Q2期间有以下海运需求，烦请提供最新报价：\n\n1. 上海 → 大阪  FCL 20'  电子产品  月均5柜\n2. 上海 → 东京  FCL 40'  电子产品  月均3柜\n3. 深圳 → 名古屋  LCL  样品件  不定期\n\n请提供：\n- 海运费\n- 各项附加费明细\n- 有效期\n- 预计船期\n\n希望能在2月底前收到报价。\n\n谢谢！\n张伟\nABC电子有限公司 物流部",
    "has_attachment": false,
    "attachment_names": [],
    "language": "zh",
    "category": "rate_inquiry",
    "tags": ["询价", "上海", "大阪", "东京", "深圳", "名古屋", "电子产品"]
  },
  {
    "id": "EMAIL-019",
    "from": "wang.lei@hankyuhanshin-sh.cn",
    "from_name": "王磊",
    "to": ["zhang.wei@customer-abc.cn"],
    "cc": ["suzuki.kenji@hankyuhanshin-exp.co.jp"],
    "date": "2026-02-25T16:30:00+08:00",
    "subject": "Re: ABC电子 2026年Q2海运询价",
    "body": "张伟先生：\n\n感谢您的询价，以下是我司最新报价：\n\n1. 上海→大阪 FCL 20'\n   海运费: USD 320/20'\n   THC(上海): CNY 750/20'\n   THC(大阪): JPY 25,000/20'\n   DOC Fee: USD 35/BL\n   船期: 每周三/六  航程约3天\n   船公司: ONE / COSCO\n\n2. 上海→东京 FCL 40'\n   海运费: USD 580/40'\n   THC(上海): CNY 800/40'\n   THC(东京): JPY 38,000/40'\n   DOC Fee: USD 35/BL\n   船期: 每周二/五  航程约4天\n   船公司: ONE / Evergreen\n\n3. 深圳→名古屋 LCL\n   海运费: USD 55/CBM (min 2 CBM)\n   CFS费(深圳): CNY 25/CBM\n   CFS费(名古屋): JPY 3,800/CBM\n   DOC Fee: USD 40/BL\n   船期: 每周四  航程约7天\n\n以上费率有效期: 2026/04/01 - 2026/06/30\n\n如有疑问请随时联系。\n\n王磊\n阪急阪神国际货运（上海）",
    "has_attachment": false,
    "attachment_names": [],
    "language": "zh",
    "category": "rate_response",
    "tags": ["报价回复", "上海", "大阪", "东京", "深圳", "名古屋", "ONE", "COSCO"]
  },
  {
    "id": "EMAIL-020",
    "from": "fukuyama.akira@hankyuhanshin-exp.co.jp",
    "from_name": "福山 明",
    "to": ["suzuki.kenji@hankyuhanshin-exp.co.jp", "tanaka.yuki@hankyuhanshin-exp.co.jp"],
    "cc": [],
    "date": "2026-03-01T09:00:00+09:00",
    "subject": "2026年度入札案件 進捗状況一覧",
    "body": "各位\n\n福山です。\n2026年度入札案件の進捗状況を整理しました。\n\n【完了案件】\n✓ トヨタ自動車 海上輸送（1/31提出済み）\n✓ パナソニック 欧州向け海上輸送（3/3提出済み）\n\n【進行中】\n△ 本田技研 航空輸送（回答期限: 2/20）→ 費率収集済み、入力中\n△ 日立製作所 東南アジア向け（回答期限: 3/15）→ 各拠点へ確認中\n\n【今後の予定】\n○ ソニー 北米向け海上/航空 → 3月中旬RFQ予定\n○ 三菱電機 中国向け → 3月下旬RFQ予定\n\n今月は案件が集中しています。\n各拠点への費率確認は早めにお願いいたします。\n\n以上",
    "has_attachment": false,
    "attachment_names": [],
    "language": "ja",
    "category": "internal_report",
    "tags": ["進捗", "入札一覧", "トヨタ", "パナソニック", "Honda", "日立", "ソニー", "三菱電機"]
  },
  {
    "id": "EMAIL-021",
    "from": "tanaka.yuki@hankyuhanshin-exp.co.jp",
    "from_name": "田中 裕樹",
    "to": ["wang.lei@hankyuhanshin-sh.cn", "li.wei@hankyuhanshin-bj.cn"],
    "cc": ["suzuki.kenji@hankyuhanshin-exp.co.jp"],
    "date": "2026-03-02T10:30:00+09:00",
    "subject": "【至急】日立製作所 東南アジア向け海上輸送 費率確認",
    "body": "王さん、李さん\n\nお疲れ様です。田中です。\n\n日立製作所様より東南アジア向け入札の依頼が来ています。\n至急、以下の航路の費率確認をお願いします。\n\n1. 横浜→シンガポール FCL 40'\n2. 横浜→ジャカルタ FCL 40'\n3. 名古屋→マニラ FCL 20'\n4. 大阪→ホーチミン FCL 20'/40'\n5. 神戸→バンコク LCL\n\n工業機械が主な貨物です。重量物の可能性があるため、\n重量制限の確認もお願いいたします。\n\n回答期限：3月10日\n（顧客提出期限：3月15日）\n\n急ぎで恐縮ですが、よろしくお願いいたします。",
    "has_attachment": false,
    "attachment_names": [],
    "language": "ja",
    "category": "rate_inquiry",
    "tags": ["至急", "日立", "東南アジア", "シンガポール", "ジャカルタ", "マニラ", "ホーチミン", "バンコク"]
  },
  {
    "id": "EMAIL-022",
    "from": "wang.lei@hankyuhanshin-sh.cn",
    "from_name": "王磊",
    "to": ["tanaka.yuki@hankyuhanshin-exp.co.jp"],
    "cc": ["suzuki.kenji@hankyuhanshin-exp.co.jp"],
    "date": "2026-03-07T09:15:00+08:00",
    "subject": "Re: 【至急】日立製作所 東南アジア向け 費率回答（上海分）",
    "body": "田中さん\n\n上海の王です。シンガポール・ジャカルタ向けの費率です。\n現地代理店に確認済みです。\n\n①横浜→シンガポール FCL 40'\n  Ocean Freight: USD 620/40'\n  BAF: USD 95/40'\n  THC(横浜): JPY 38,000/40'\n  THC(シンガポール): SGD 280/40'\n  DOC Fee: USD 35/BL\n  T/T: 8-10日\n  船社: ONE / Yang Ming\n  ※重量制限: 40'コンテナ max 26,000kg\n\n②横浜→ジャカルタ(タンジュンプリオク) FCL 40'\n  Ocean Freight: USD 750/40'\n  BAF: USD 110/40'\n  THC(横浜): JPY 38,000/40'\n  THC(ジャカルタ): USD 180/40'\n  DOC Fee: USD 35/BL\n  T/T: 12-14日\n  船社: Evergreen / PIL\n  ※重量制限: 40'コンテナ max 24,000kg（ジャカルタ港制限）\n\n有効期間: 2026/04/01 - 2026/09/30\n\nよろしくお願いいたします。",
    "has_attachment": false,
    "attachment_names": [],
    "language": "ja",
    "category": "rate_response",
    "tags": ["費率回答", "横浜", "シンガポール", "ジャカルタ", "ONE", "Yang Ming", "Evergreen"]
  },
  {
    "id": "EMAIL-023",
    "from": "li.wei@hankyuhanshin-bj.cn",
    "from_name": "李伟",
    "to": ["tanaka.yuki@hankyuhanshin-exp.co.jp"],
    "cc": ["suzuki.kenji@hankyuhanshin-exp.co.jp"],
    "date": "2026-03-08T14:00:00+08:00",
    "subject": "Re: 日立 東南アジア向け 費率回答（マニラ/ホーチミン/バンコク）",
    "body": "田中さん\n\n北京の李です。残りの航路の費率です。\n\n③名古屋→マニラ FCL 20'\n  Ocean Freight: USD 350/20'\n  BAF: USD 55/20'\n  THC(名古屋): JPY 25,000/20'\n  THC(マニラ): PHP 12,000/20'\n  DOC Fee: USD 35/BL\n  T/T: 7-9日\n  船社: ONE / Wan Hai\n\n④大阪→ホーチミン\n  FCL 20': Ocean Freight USD 380/20' + BAF USD 60/20'\n  FCL 40': Ocean Freight USD 560/40' + BAF USD 90/40'\n  THC(大阪): JPY 25,000/20', JPY 38,000/40'\n  THC(ホーチミン): USD 120/20', USD 160/40'\n  T/T: 10-12日\n  船社: Evergreen / Wan Hai\n\n⑤神戸→バンコク LCL\n  Ocean Freight: USD 48/CBM\n  CFS(神戸): JPY 3,800/CBM\n  CFS(バンコク): THB 800/CBM\n  DOC Fee: USD 40/BL\n  T/T: 14-16日\n\n全航路 有効期間: 2026/04/01 - 2026/09/30\n重量制限については各航路とも標準範囲内であれば問題なしです。\n\nよろしくお願いいたします。",
    "has_attachment": false,
    "attachment_names": [],
    "language": "ja",
    "category": "rate_response",
    "tags": ["費率回答", "名古屋", "マニラ", "大阪", "ホーチミン", "神戸", "バンコク"]
  },
  {
    "id": "EMAIL-024",
    "from": "chen.ming@hankyuhanshin-sh.cn",
    "from_name": "陈明",
    "to": ["suzuki.kenji@hankyuhanshin-exp.co.jp", "fukuyama.akira@hankyuhanshin-exp.co.jp"],
    "cc": [],
    "date": "2026-03-10T10:00:00+08:00",
    "subject": "3月海运市场动态 - 亚洲区域总结",
    "body": "鈴木课长、福山部长：\n\n你们好，以下是3月亚洲海运市场的主要动态：\n\n【运力情况】\n- 亚洲→欧洲：GRI已生效，但实际涨幅低于预期，船公司开始提供折扣\n- 亚洲→北美：太平洋航线运价持续走弱，竞争激烈\n- 亚洲区域内（日本↔中国/东南亚）：运价平稳，舱位充足\n\n【值得关注】\n1. COSCO和Evergreen联盟调整，4月起部分亚欧航线班期变更\n2. 日本→东南亚方向，越南线需求增长明显（制造业转移趋势）\n3. 红海局势趋于稳定，苏伊士运河通行恢复正常，欧线transit time缩短\n\n【对业务的影响】\n- 欧洲向け入札：可适当下调报价争取份额\n- 东南亚向け：越南线建议提前锁定舱位\n- 北美向け：观望态度，运价可能继续下行\n\n详细数据报告见附件。\n\n陈明\n阪急阪神国际货运（上海）",
    "has_attachment": true,
    "attachment_names": ["202603_亚洲海运市场报告.pdf"],
    "language": "zh",
    "category": "market_intelligence",
    "tags": ["市场动态", "GRI", "COSCO", "Evergreen", "运力", "欧洲", "北美", "东南亚"]
  },
  {
    "id": "EMAIL-025",
    "from": "sony.scm@sony.com",
    "from_name": "ソニー SCM部",
    "to": ["suzuki.kenji@hankyuhanshin-exp.co.jp"],
    "cc": [],
    "date": "2026-03-12T11:00:00+09:00",
    "subject": "【RFQ】ソニー 2026年度下期 北米向け海上/航空輸送",
    "body": "阪急阪神エクスプレス\n鈴木様\n\nお世話になっております。ソニーSCM部です。\n\n2026年度下期（10月～3月）の北米向け輸送について見積をお願いいたします。\n\n【海上輸送】\n1. 横浜→ロングビーチ FCL 40'HC  家電・ゲーム機  月間20 FEU\n2. 大阪→ロサンゼルス FCL 40'   部品類  月間8 FEU\n3. 名古屋→ニューヨーク/ニューアーク FCL 40'  月間5 FEU\n\n【航空輸送】\n4. 成田→JFK  電子機器（緊急出荷用）500kg+/月\n5. 関空→LAX  サンプル品 100kg+/月\n\n回答期限：2026年4月10日\nフォーマット：添付Excel\n\nボリュームディスカウントの可否もご提案ください。\n\nよろしくお願いいたします。",
    "has_attachment": true,
    "attachment_names": ["Sony_NorthAmerica_RFQ_2026H2.xlsx"],
    "language": "ja",
    "category": "bidding_request",
    "tags": ["入札", "ソニー", "北米", "ロングビーチ", "ロサンゼルス", "ニューヨーク", "航空", "海上"]
  },
  {
    "id": "EMAIL-026",
    "from": "tanaka.yuki@hankyuhanshin-exp.co.jp",
    "from_name": "田中 裕樹",
    "to": ["john.smith@hankyuhanshin-us.com"],
    "cc": ["suzuki.kenji@hankyuhanshin-exp.co.jp"],
    "date": "2026-03-13T09:30:00+09:00",
    "subject": "Urgent Rate Request: Japan → US West/East Coast (Sony RFQ)",
    "body": "Hi John,\n\nWe've received a significant RFQ from Sony for their 2026 H2 North America shipments.\nThis is a high-priority account with substantial volume.\n\nSea Freight lanes needed:\n1. Yokohama → Long Beach FCL 40'HC (20 FEU/month)\n2. Osaka → Los Angeles FCL 40' (8 FEU/month)\n3. Nagoya → New York/Newark FCL 40' (5 FEU/month)\n\nAir Freight lanes needed:\n4. NRT → JFK 500kg+/month (emergency shipments)\n5. KIX → LAX 100kg+/month (samples)\n\nPlease provide:\n- Best rates considering the volume commitment\n- Volume discount tiers if available\n- All-in rates preferred (incl. all surcharges)\n- Validity: Oct 2026 - Mar 2027\n\nDeadline for your response: March 31\n(Customer deadline: April 10)\n\nThis is a must-win account. Please give us your most competitive rates.\n\nThanks,\nYuki Tanaka",
    "has_attachment": false,
    "attachment_names": [],
    "language": "en",
    "category": "rate_inquiry",
    "tags": ["urgent", "Sony", "US", "Long Beach", "Los Angeles", "New York", "volume_discount"]
  },
  {
    "id": "EMAIL-027",
    "from": "suzuki.kenji@hankyuhanshin-exp.co.jp",
    "from_name": "鈴木 健二",
    "to": ["tanaka.yuki@hankyuhanshin-exp.co.jp"],
    "cc": [],
    "date": "2026-03-13T17:30:00+09:00",
    "subject": "Re: ソニー案件 対応方針について",
    "body": "田中さん\n\nソニー案件について方針を共有します。\n\n・ソニーは当社の重要顧客で、年間取引額上位5社に入ります\n・北米向けは現在市況が軟調なため、攻めの価格設定が可能\n・ボリュームディスカウントは月間30FEU以上で2-3%を提案\n・航空輸送はスポット的な利用なので標準レートで問題なし\n\n注意点：\n・ロングビーチの港湾混雑が解消傾向にあり、Demurrage/Detentionリスクは低下\n・ただしニューヨーク向けはパナマ運河の水位制限の影響で、\n  スエズ経由のルートも検討してください\n\n米国現法からの回答が来たら、すり合わせしましょう。\n\n鈴木",
    "has_attachment": false,
    "attachment_names": [],
    "language": "ja",
    "category": "internal_discussion",
    "tags": ["ソニー", "方針", "北米", "ボリュームディスカウント", "パナマ運河"]
  },
  {
    "id": "EMAIL-028",
    "from": "fukuyama.akira@hankyuhanshin-exp.co.jp",
    "from_name": "福山 明",
    "to": ["suzuki.kenji@hankyuhanshin-exp.co.jp"],
    "cc": [],
    "date": "2026-03-15T08:00:00+09:00",
    "subject": "三菱電機様 中国向け入札 事前情報",
    "body": "鈴木さん\n\n福山です。\n三菱電機様から来週RFQが届く予定です。事前情報を共有します。\n\n概要：\n・対象：中国向け海上輸送（FCL中心）\n・航路：名古屋/大阪→上海/青島/大連/広州\n・貨物：産業用ロボット部品、FA機器\n・数量：月間15-20 TEU\n・期間：2026年下期（10月～3月）\n\n注意点：\n・三菱電機は価格よりリードタイムと安定性を重視する傾向\n・昨年度は当社とDHL、日通の3社コンペでした\n・昨年度の当社提出価格を参考として添付します\n\n王さんと陳さんに事前に費率感触を確認しておいてもらえると\nスムーズに対応できると思います。\n\nよろしくお願いします。",
    "has_attachment": true,
    "attachment_names": ["三菱電機_2025年度_見積参考.xlsx"],
    "language": "ja",
    "category": "internal_discussion",
    "tags": ["三菱電機", "中国", "事前準備", "上海", "青島", "大連", "広州", "産業用ロボット"]
  },
  {
    "id": "EMAIL-029",
    "from": "suzuki.kenji@hankyuhanshin-exp.co.jp",
    "from_name": "鈴木 健二",
    "to": ["wang.lei@hankyuhanshin-sh.cn", "chen.ming@hankyuhanshin-sh.cn"],
    "cc": ["fukuyama.akira@hankyuhanshin-exp.co.jp"],
    "date": "2026-03-15T10:00:00+09:00",
    "subject": "【事前準備】三菱電機 中国向け 費率事前確認",
    "body": "王さん、陳さん\n\n鈴木です。\n\n三菱電機様の中国向け入札が来週予定されています。\n事前に以下の航路の最新費率感触を確認させてください。\n（正式なRFQ受領後に再度正式依頼します）\n\n1. 名古屋→上海  FCL 20'/40'\n2. 名古屋→青島  FCL 20'/40'\n3. 大阪→大連   FCL 20'/40'\n4. 大阪→広州（南沙）FCL 20'/40'\n\n特に気になる点：\n・最近の日中航路の運賃トレンド\n・船社スペースの安定性\n・リードタイム（直行便 vs トランシップ）\n\n来週月曜までに概算レベルで構いませんのでご回答ください。\n\nよろしくお願いいたします。",
    "has_attachment": false,
    "attachment_names": [],
    "language": "ja",
    "category": "rate_inquiry",
    "tags": ["三菱電機", "事前確認", "名古屋", "上海", "青島", "大阪", "大連", "広州"]
  },
  {
    "id": "EMAIL-030",
    "from": "chen.ming@hankyuhanshin-sh.cn",
    "from_name": "陈明",
    "to": ["suzuki.kenji@hankyuhanshin-exp.co.jp"],
    "cc": ["wang.lei@hankyuhanshin-sh.cn", "fukuyama.akira@hankyuhanshin-exp.co.jp"],
    "date": "2026-03-17T11:30:00+08:00",
    "subject": "Re: 三菱電機 中国向け 費率概算回答",
    "body": "鈴木课长：\n\n陈明です。概算费率をお送りします。\n\n現状の日中航路トレンド：\n・運賃は安定～やや下落傾向\n・舱位充足、スペース問題なし\n・直行便は上海・大連向けが充実、青島・広州はトランシップの場合あり\n\n概算费率（参考値）：\n\n①名古屋→上海\n  FCL 20': USD 250-280\n  FCL 40': USD 400-450\n  直行便あり T/T 3-4日\n\n②名古屋→青島\n  FCL 20': USD 280-320\n  FCL 40': USD 450-520\n  直行便あり T/T 4-5日\n  ※青島港の通関が最近厳しくなっている情報あり\n\n③大阪→大連\n  FCL 20': USD 230-260\n  FCL 40': USD 380-430\n  直行便あり T/T 3日\n\n④大阪→広州（南沙）\n  FCL 20': USD 320-360\n  FCL 40': USD 520-580\n  上海トランシップ T/T 7-9日\n  ※直行便は隔週のみ\n\n主要船社: COSCO / ONE / SITC / T.S. Lines\n\n正式RFQ来次第、確定费率をお送りします。\n\n陈明",
    "has_attachment": false,
    "attachment_names": [],
    "language": "ja",
    "category": "rate_response",
    "tags": ["三菱電機", "概算", "名古屋", "上海", "青島", "大阪", "大連", "広州", "COSCO", "ONE"]
  },
  {
    "id": "EMAIL-031",
    "from": "tanaka.yuki@hankyuhanshin-exp.co.jp",
    "from_name": "田中 裕樹",
    "to": ["suzuki.kenji@hankyuhanshin-exp.co.jp"],
    "cc": [],
    "date": "2026-03-18T16:00:00+09:00",
    "subject": "Honda様 航空輸送入札 提出完了",
    "body": "鈴木課長\n\nお疲れ様です。\n\n本田技研様の航空輸送入札、本日提出完了しました。\n（回答期限2/20に対し遅延がありましたが、先方了承済みです）\n\n最終提出内容：\n1. NRT→LAX: Korean Air経由 JPY 650/kg（コスト重視）\n   ※ANA直行便 JPY 780/kgも併記\n2. NRT→ORD: Korean Air経由 JPY 720/kg\n3. KIX→BKK: Thai Airways JPY 450/kg\n4. NRT→PVG: Air China JPY 350/kg\n\n先方からは「4月上旬に選定結果を連絡する」とのことです。\n\n以上、ご報告まで。",
    "has_attachment": true,
    "attachment_names": ["Honda_AirFreight_2026_HHE回答_final.xlsx"],
    "language": "ja",
    "category": "bidding_response",
    "tags": ["入札完了", "Honda", "航空", "Korean Air", "ANA", "Thai Airways", "Air China"]
  },
  {
    "id": "EMAIL-032",
    "from": "wang.lei@hankyuhanshin-sh.cn",
    "from_name": "王磊",
    "to": ["suzuki.kenji@hankyuhanshin-exp.co.jp"],
    "cc": [],
    "date": "2026-03-19T08:45:00+08:00",
    "subject": "COSCO 4月份运价调整通知",
    "body": "鈴木课长：\n\n早上好。收到COSCO的通知，4月起以下航线运价调整：\n\n【下调】\n- 上海→日本各港: FCL 20' 下调 USD 30, FCL 40' 下调 USD 50\n- 青島→日本各港: FCL 20' 下调 USD 25, FCL 40' 下调 USD 40\n\n【上调】\n- 上海→东南亚各港: FCL 全规格上调 USD 50-80\n  原因：东南亚制造业需求旺盛，舱位紧张\n\n【不变】\n- 日本→中国各港: 维持现有运价\n- 大连/广州相关航线: 维持不变\n\n生效日期：2026/04/01\n\n这对三菱电机的报价可能有影响，建议关注。\n\n王磊",
    "has_attachment": false,
    "attachment_names": [],
    "language": "zh",
    "category": "rate_change_notice",
    "tags": ["COSCO", "运价调整", "上海", "日本", "东南亚", "三菱電機"]
  },
  {
    "id": "EMAIL-033",
    "from": "fukuyama.akira@hankyuhanshin-exp.co.jp",
    "from_name": "福山 明",
    "to": ["suzuki.kenji@hankyuhanshin-exp.co.jp", "tanaka.yuki@hankyuhanshin-exp.co.jp"],
    "cc": [],
    "date": "2026-03-20T09:00:00+09:00",
    "subject": "【注意喚起】入札業務 よくあるミスと対策",
    "body": "各位\n\n福山です。\n最近の入札業務で気になった点を共有します。\n\n【よくあるミス】\n1. 通貨の入力ミス（USDとJPYの取り違え）\n2. 有効期間の記載漏れ\n3. THCの積地/揚地の混同\n4. サーチャージの計算ミス（%計算 vs 固定額）\n5. 旧費率での回答（最新費率を反映していない）\n\n【対策】\n・入力後のダブルチェック体制の徹底\n・費率回答メールの日付確認（古いメールの費率を使っていないか）\n・提出前に通貨単位を再確認\n・テンプレートの更新日を確認\n\n上記はシステム化・自動化で大幅に改善できる領域だと考えています。\nDHC社との効率化プロジェクトに期待しています。\n\n以上",
    "has_attachment": false,
    "attachment_names": [],
    "language": "ja",
    "category": "internal_report",
    "tags": ["注意喚起", "入札ミス", "改善", "自動化"]
  },
  {
    "id": "EMAIL-034",
    "from": "yamamoto.keiko@hankyuhanshin-exp.co.jp",
    "from_name": "山本 恵子",
    "to": ["suzuki.kenji@hankyuhanshin-exp.co.jp"],
    "cc": ["fukuyama.akira@hankyuhanshin-exp.co.jp"],
    "date": "2026-03-20T14:00:00+09:00",
    "subject": "トヨタ自動車様 入札結果通知",
    "body": "鈴木課長\n\n営業部の山本です。\n\nトヨタ自動車様より2026年度上期の入札結果が届きました。\n\n【結果】\n✓ 名古屋→上海 FCL 40' → 当社受注！\n✗ 名古屋→天津 FCL 40' → 日通に決定（当社より約5%安い提示だった模様）\n✓ 横浜→バンコク FCL 20'/40' → 当社受注！\n✗ 神戸→ホーチミン LCL → 近鉄エクスプレスに決定\n\n受注率: 2/4 = 50%\n\n天津の件は価格差が小さかったため、次回はもう少し攻めた価格設定が必要かもしれません。\nホーチミンLCLは近鉄が強いルートなので、現地コスト構造の見直しが課題です。\n\n詳細は添付の通知書をご確認ください。",
    "has_attachment": true,
    "attachment_names": ["トヨタ_2026上期_入札結果通知.pdf"],
    "language": "ja",
    "category": "bidding_result",
    "tags": ["入札結果", "トヨタ", "受注", "失注", "名古屋", "上海", "バンコク"]
  },
  {
    "id": "EMAIL-035",
    "from": "suzuki.kenji@hankyuhanshin-exp.co.jp",
    "from_name": "鈴木 健二",
    "to": ["wang.lei@hankyuhanshin-sh.cn", "nguyen.van.duc@hankyuhanshin-vn.com"],
    "cc": ["fukuyama.akira@hankyuhanshin-exp.co.jp"],
    "date": "2026-03-21T09:00:00+09:00",
    "subject": "Toyota Bid Result & Cost Review Request",
    "body": "Dear Wang-san, Duc-san,\n\nSharing the Toyota 2026 H1 bid results:\n\nWON:\n- Nagoya → Shanghai FCL 40' (our rate: USD 850)\n- Yokohama → Bangkok FCL 20'/40' (our rate: USD 380/580)\n\nLOST:\n- Nagoya → Tianjin FCL 40' (lost to Nippon Express by ~5%)\n- Kobe → Ho Chi Minh LCL (lost to Kintetsu Express)\n\nAction items:\n1. Wang-san: Please review Tianjin cost structure.\n   Can we get a better rate from COSCO or alternative carriers?\n   We need to be more competitive next round.\n\n2. Duc-san: Please review HCM LCL costs.\n   Kintetsu seems to have a structural cost advantage on this lane.\n   Can we explore co-loader options or different CFS operators?\n\nLet's discuss in next week's call.\n\nRegards,\nKenji Suzuki",
    "has_attachment": false,
    "attachment_names": [],
    "language": "en",
    "category": "internal_discussion",
    "tags": ["Toyota", "bid_result", "cost_review", "Tianjin", "Ho Chi Minh"]
  },
  {
    "id": "EMAIL-036",
    "from": "hitachi.logistics@hitachi.co.jp",
    "from_name": "日立製作所 物流管理部",
    "to": ["suzuki.kenji@hankyuhanshin-exp.co.jp"],
    "cc": [],
    "date": "2026-03-22T10:00:00+09:00",
    "subject": "日立製作所 東南アジア向け入札 選考結果",
    "body": "阪急阪神エクスプレス\n鈴木様\n\nお世話になっております。日立製作所 物流管理部です。\n\n東南アジア向け海上輸送の入札選考結果をご連絡いたします。\n\n【選考結果】\n✓ 横浜→シンガポール FCL 40' → 貴社に決定\n✓ 横浜→ジャカルタ FCL 40' → 貴社に決定\n✓ 名古屋→マニラ FCL 20' → 貴社に決定\n△ 大阪→ホーチミン FCL → 貴社とDHLの併用\n✗ 神戸→バンコク LCL → 郵船ロジスティクスに決定\n\n貴社には安定したサービスとリードタイムを高く評価いただきました。\n契約書は別途お送りいたします。\n\n今後ともよろしくお願いいたします。",
    "has_attachment": false,
    "attachment_names": [],
    "language": "ja",
    "category": "bidding_result",
    "tags": ["入札結果", "日立", "シンガポール", "ジャカルタ", "マニラ", "ホーチミン", "受注"]
  },
  {
    "id": "EMAIL-037",
    "from": "tanaka.yuki@hankyuhanshin-exp.co.jp",
    "from_name": "田中 裕樹",
    "to": ["suzuki.kenji@hankyuhanshin-exp.co.jp", "fukuyama.akira@hankyuhanshin-exp.co.jp"],
    "cc": [],
    "date": "2026-03-22T14:30:00+09:00",
    "subject": "2026年度 入札実績サマリー（3月22日時点）",
    "body": "鈴木課長、福山部長\n\nお疲れ様です。3月22日時点の入札実績をまとめました。\n\n【受注実績】\n                                    受注/応札  受注率\nトヨタ自動車（海上）                   2/4      50%\n日立製作所（東南アジア海上）           3.5/5    70%\n本田技研（航空）                      結果待ち\nパナソニック（欧州海上）               結果待ち\n\n【受注額（概算）】\n・トヨタ: 約 USD 180,000/年\n・日立: 約 USD 350,000/年\n\n【失注分析】\n・価格競争力: 天津向け（日通に-5%）、バンコクLCL（郵船ロジ）\n・地域偏り: ベトナム向けLCLは競合が強い\n\n【改善提案】\n1. 天津/ベトナム向けの現地コスト見直し\n2. LCL案件の現地パートナー拡充\n3. 入札回答のスピードアップ（今回Honda案件で遅延あり）\n\n以上、ご確認ください。",
    "has_attachment": false,
    "attachment_names": [],
    "language": "ja",
    "category": "internal_report",
    "tags": ["入札実績", "サマリー", "受注率", "トヨタ", "日立", "改善提案"]
  },
  {
    "id": "EMAIL-038",
    "from": "wang.lei@hankyuhanshin-sh.cn",
    "from_name": "王磊",
    "to": ["suzuki.kenji@hankyuhanshin-exp.co.jp"],
    "cc": [],
    "date": "2026-03-23T09:00:00+08:00",
    "subject": "天津向け コスト改善提案",
    "body": "鈴木课长：\n\n关于天津航线竞争力不足的问题，我做了一些调查：\n\n【现状分析】\n- 我们目前主要使用ONE，运价 USD 920/40'\n- 日通可能使用COSCO直约价，估计在 USD 860-870/40'\n\n【改善方案】\n1. COSCO签约：如果年间承诺量达到200 TEU，可获得约 USD 850/40' 的合约价\n2. SITC Lines：天津航线有价格优势，约 USD 830/40'，但T/T多1-2天\n3. 拼单方案：与其他客户的天津货物合并，争取更优惠的费率\n\n【建议】\n优先推进COSCO签约，既能降低成本又能保证服务稳定性。\n如果鈴木课长同意，我可以联系COSCO华北区销售洽谈。\n\n王磊",
    "has_attachment": false,
    "attachment_names": [],
    "language": "zh",
    "category": "internal_discussion",
    "tags": ["天津", "成本改善", "COSCO", "SITC", "竞争力"]
  },
  {
    "id": "EMAIL-039",
    "from": "nguyen.van.duc@hankyuhanshin-vn.com",
    "from_name": "Nguyen Van Duc",
    "to": ["suzuki.kenji@hankyuhanshin-exp.co.jp"],
    "cc": [],
    "date": "2026-03-23T15:00:00+07:00",
    "subject": "Re: HCM LCL Cost Review - Alternative Options",
    "body": "Dear Suzuki-san,\n\nI've reviewed our Ho Chi Minh LCL cost structure as requested.\n\nCurrent situation:\n- We use ABC Logistics as our CFS operator\n- Our all-in cost: approx. USD 52/CBM (Kobe → HCM)\n- Kintetsu's estimated rate: USD 42-45/CBM\n\nTheir advantage:\n- Kintetsu has their own CFS warehouse in HCM (no third-party costs)\n- Higher LCL consolidation volume = better ocean rates\n\nOur options:\n1. Switch CFS operator to VN Express (quoted USD 5/RT vs current USD 8/RT)\n   → Saves about USD 3/CBM, bringing us to ~USD 49/CBM\n\n2. Partner with a local co-loader (Vinalink or Gemadept)\n   → Could reduce ocean freight by USD 5-8/CBM\n   → But quality control risk\n\n3. Build our own consolidation volume\n   → Long-term solution, needs sales push in Vietnam import market\n\nRecommendation: Option 1 as immediate action, Option 3 as long-term strategy.\n\nBest regards,\nDuc",
    "has_attachment": false,
    "attachment_names": [],
    "language": "en",
    "category": "internal_discussion",
    "tags": ["Ho Chi Minh", "LCL", "cost_review", "CFS", "co-loader", "Kintetsu"]
  },
  {
    "id": "EMAIL-040",
    "from": "mitsubishi.procurement@melco.co.jp",
    "from_name": "三菱電機 調達本部",
    "to": ["suzuki.kenji@hankyuhanshin-exp.co.jp"],
    "cc": [],
    "date": "2026-03-24T09:00:00+09:00",
    "subject": "【RFQ】三菱電機 2026年度下期 中国向け海上輸送入札",
    "body": "阪急阪神エクスプレス\n鈴木様\n\nお世話になっております。三菱電機 調達本部です。\n\n2026年度下期の中国向け海上輸送につき、見積をお願いいたします。\n\n対象航路：\n1. 名古屋→上海 FCL 20'/40'  産業用ロボット部品\n2. 名古屋→青島 FCL 20'/40'  FA機器\n3. 大阪→大連 FCL 20'/40'  半導体製造装置部品\n4. 大阪→広州(南沙) FCL 20'/40'  エレベーター部品\n\n月間予定数量：合計15-20 TEU\n契約期間：2026年10月～2027年3月\n\n重要条件：\n・直行便を優先（特に大連・上海）\n・リードタイムの安定性を重視\n・保険手配の可否\n\n回答期限：2026年4月8日\nフォーマット：添付Excel\n\n何卒よろしくお願いいたします。",
    "has_attachment": true,
    "attachment_names": ["三菱電機_中国向け_RFQ_2026H2.xlsx"],
    "language": "ja",
    "category": "bidding_request",
    "tags": ["入札", "三菱電機", "中国", "名古屋", "上海", "青島", "大阪", "大連", "広州"]
  },
  {
    "id": "EMAIL-041",
    "from": "suzuki.kenji@hankyuhanshin-exp.co.jp",
    "from_name": "鈴木 健二",
    "to": ["wang.lei@hankyuhanshin-sh.cn", "chen.ming@hankyuhanshin-sh.cn"],
    "cc": ["fukuyama.akira@hankyuhanshin-exp.co.jp", "tanaka.yuki@hankyuhanshin-exp.co.jp"],
    "date": "2026-03-24T10:30:00+09:00",
    "subject": "【正式依頼】三菱電機 中国向け 費率確認",
    "body": "王さん、陳さん\n\n鈴木です。\n三菱電機様より正式RFQが届きました（先日の事前情報通り）。\n\n正式に以下の費率確認をお願いいたします。\n前回の概算回答をベースに、確定費率をお願いします。\n\n1. 名古屋→上海 FCL 20'/40'\n2. 名古屋→青島 FCL 20'/40'\n3. 大阪→大連 FCL 20'/40'\n4. 大阪→広州(南沙) FCL 20'/40'\n\n重要ポイント：\n・三菱電機は直行便・リードタイム重視です\n・先日のCOSCO 4月運賃改定も反映してください\n・昨年度より競争力ある価格を目指します\n\n回答期限：4月1日（顧客期限：4月8日）\n\nよろしくお願いいたします。",
    "has_attachment": true,
    "attachment_names": ["三菱電機_中国向け_RFQ_2026H2.xlsx"],
    "language": "ja",
    "category": "rate_inquiry",
    "tags": ["三菱電機", "正式依頼", "名古屋", "上海", "青島", "大阪", "大連", "広州"]
  },
  {
    "id": "EMAIL-042",
    "from": "chen.ming@hankyuhanshin-sh.cn",
    "from_name": "陈明",
    "to": ["suzuki.kenji@hankyuhanshin-exp.co.jp"],
    "cc": ["wang.lei@hankyuhanshin-sh.cn", "fukuyama.akira@hankyuhanshin-exp.co.jp"],
    "date": "2026-03-25T16:00:00+08:00",
    "subject": "三菱電機 中国向け 最新费率一览",
    "body": "鈴木课长：\n\n陈明です。三菱電機案件の確定費率です。\nCOSCO 4月改定も反映済みです。\n\n①名古屋→上海\n  FCL 20': USD 240/20' (概算 250-280から改善)\n  FCL 40': USD 390/40' (概算 400-450から改善)\n  船社: COSCO（4月値下げ反映）/ ONE\n  T/T: 3-4日（直行便）\n  THC(名古屋): JPY 25,000/20', JPY 35,000/40'\n  THC(上海): CNY 700/20', CNY 800/40'\n\n②名古屋→青島\n  FCL 20': USD 270/20'\n  FCL 40': USD 440/40'\n  船社: COSCO / SITC\n  T/T: 4-5日（直行便）\n  ※青島通関厳格化の件、現時点では大きな影響なし\n\n③大阪→大連\n  FCL 20': USD 220/20'\n  FCL 40': USD 370/40'\n  船社: COSCO / SITC\n  T/T: 3日（直行便、週2便）\n\n④大阪→広州（南沙）\n  FCL 20': USD 310/20'\n  FCL 40': USD 510/40'\n  船社: COSCO（上海トランシップ）\n  T/T: 7-9日\n  ※直行便は隔週SITC便のみ、T/T 5日\n\n全航路共通:\n  DOC Fee: USD 35/BL\n  BAF: 込み\n  有効期間: 2026/10/01 - 2027/03/31\n\n去年对比で平均5-8%のコスト削減が見込めます。\n\n陈明",
    "has_attachment": false,
    "attachment_names": [],
    "language": "ja",
    "category": "rate_response",
    "tags": ["三菱電機", "確定費率", "名古屋", "上海", "青島", "大阪", "大連", "広州", "COSCO"]
  }
]
